pymmcore/__init__.pyi
pymmcore/_version.py
pymmcore/__init__.py
pymmcore/_pymmcore_swig.cpython-312-darwin.so
pymmcore/py.typed
pymmcore/pymmcore_swig_wrap.cpp
pymmcore/pymmcore_swig_wrap.h
pymmcore/pymmcore_swig.py
pymmcore-11.10.0.74.0.dist-info/RECORD
pymmcore-11.10.0.74.0.dist-info/WHEEL
pymmcore-11.10.0.74.0.dist-info/METADATA
