Metadata-Version: 2.1
Name: pymmcore
Version: 11.10.0.74.0
Summary: Python bindings for MMCore, Micro-Manager's device control layer
Author: Micro-Manager Team
License: LGPL-2.1-only
Classifier: Development Status :: 5 - Production/Stable
Classifier: Intended Audience :: Science/Research
Classifier: License :: OSI Approved :: GNU Lesser General Public License v2 (LGPLv2)
Classifier: Operating System :: MacOS :: MacOS X
Classifier: Operating System :: Microsoft :: Windows
Classifier: Operating System :: POSIX :: Linux
Classifier: Programming Language :: Python :: 3
Classifier: Programming Language :: Python :: Implementation :: CPython
Classifier: Topic :: Scientific/Engineering
Classifier: Topic :: System :: Hardware :: Hardware Drivers
Classifier: Typing :: Typed
Project-URL: homepage, https://micro-manager.org
Project-URL: repository, https://github.com/micro-manager/pymmcore
Requires-Python: >=3.9
Requires-Dist: numpy>=1.25
Provides-Extra: test
Requires-Dist: pytest; extra == "test"
